{
    "id": "coin-12240",
    "title_display": "Coin: 12240",
    "pub_created_display": [
        "bronze, Corinth"
    ],
    "call_number_display": [
        "Coin 12240"
    ],
    "call_number_browse_s": [
        "Coin 12240"
    ],
    "location_code_s": [
        "num"
    ],
    "location": [
        "Special Collections"
    ],
    "location_display": [
        "Special Collections - Numismatics Collection"
    ],
    "format": [
        "Coin"
    ],
    "advanced_location_s": [
        "num"
    ],
    "die_axis_s": [
        "11"
    ],
    "size_s": [
        "12"
    ],
    "weight_s": [
        "1.81"
    ],
    "holdings_1display": "{\"numismatics\":{\"location\":\"Special Collections - Numismatics Collection\",\"library\":\"Special Collections\",\"location_code\":\"num\",\"call_number\":\"Coin 12240\",\"call_number_browse\":\"Coin 12240\"}}",
    "donor_s": [
        "T. Leslie Shear, Jr."
    ],
    "pub_date_start_sort": -400,
    "pub_date_end_sort": -300,
    "issue_object_type_s": [
        "coin"
    ],
    "issue_denomination_s": [
        "bronze"
    ],
    "issue_number_s": [
        "8249"
    ],
    "issue_metal_s": [
        "Bronze"
    ],
    "issue_era_s": [
        "BC"
    ],
    "issue_place_s": [
        "Corinth, Corinthia, Greece"
    ],
    "issue_city_s": [
        "Corinth"
    ],
    "issue_state_s": [
        "Corinthia"
    ],
    "issue_region_s": [
        "Greece"
    ],
    "issue_obverse_figure_s": [
        "Pegasus"
    ],
    "issue_obverse_symbol_s": [
        "coppa"
    ],
    "issue_obverse_part_s": [
        "flying"
    ],
    "issue_obverse_orientation_s": [
        "left"
    ],
    "issue_reverse_figure_s": [
        "Trident"
    ],
    "issue_reverse_symbol_s": [
        "lyre"
    ],
    "issue_reverse_orientation_s": [
        "upright"
    ],
    "issue_reverse_attributes_s": [
        "\u039c, right of trident"
    ],
    "issue_references_s": [
        "BMC Corinth  468v"
    ],
    "issue_monogram_1display": "[]",
    "hashed_id_s": [
        "7b2ffe76ab87cd06"
    ],
    "_version_": 1667138342813171712,
    "timestamp": "2020-05-19T16:50:19.439Z"
}