{"id":"coin-6378","title_display":"Coin: 6378","pub_created_display":["Didrachm, Tarentum"],"call_number_display":["Coin 6378"],"call_number_browse_s":["Coin 6378"],"location_code_s":["num"],"location":["Special Collections"],"location_display":["Special Collections - Numismatics Collection"],"format":["Coin"],"advanced_location_s":["num"],"notes_display":["F-B O: 160, R: 532"],"die_axis_s":["11"],"size_s":["22"],"weight_s":["7.72"],"holdings_1display":"{\"numismatics\":{\"location\":\"Special Collections - Numismatics Collection\",\"library\":\"Special Collections\",\"location_code\":\"num\",\"call_number\":\"Coin 6378\",\"call_number_browse\":\"Coin 6378\"}}","numismatic_accession_s":["421: 1966-01-01 Baldwin Maull"],"numismatic_provenance_s":["Frederick S. Knobloch; March 1962; $20, Fixed Price List No. 22 #9"],"pub_date_start_sort":-355,"pub_date_end_sort":-340,"issue_object_type_s":["coin"],"issue_denomination_s":["Didrachm"],"issue_metal_s":["Silver"],"issue_place_s":["Tarentum, Calabria, Italy"],"issue_city_s":["Tarentum"],"issue_state_s":["Calabria"],"issue_region_s":["Italy"],"issue_obverse_figure_s":["Rider on standing horse"],"issue_obverse_symbol_s":["K"],"issue_obverse_orientation_s":["right"],"issue_obverse_figure_description_s":["rider's left hand holds the reins, right hand crowns horse with garland; below horse's belly K and club"],"issue_reverse_figure_s":["Boy on a dolphin"],"issue_reverse_orientation_s":["left"],"issue_reverse_figure_description_s":["rider's right hand hold's holds kantharos, on left arm buckler with trident beneath; legend along upper right side; waves at bottom"],"issue_reverse_legend_s":["TARAS"],"issue_references_s":["Vlasto Coll.  508-9","F-B  685"],"issue_monogram_1display":"[]","issue_date_s":["-355 to -340"],"hashed_id_s":["894c7e3b17169db2"],"_version_":1684903259488124928,"timestamp":"2020-12-01T18:56:04.206Z"}