{"id":"coin-7321","title_display":"Coin: 7321","pub_created_display":["Constantine I (306 to 337), follis, Antioch"],"call_number_display":["Coin 7321"],"call_number_browse_s":["Coin 7321"],"location_code_s":["num"],"location":["Special Collections"],"location_display":["Special Collections - Numismatics Collection"],"format":["Coin"],"advanced_location_s":["num"],"find_place_s":["Antioch, Syria"],"find_date_s":["1932-05-26"],"find_feature_s":["House A, S. of peristyle, surface"],"find_locus_s":["DS 10-N (HSEA)"],"find_number_s":["1777a"],"die_axis_s":["5"],"size_s":["18"],"weight_s":["1.21"],"holdings_1display":"{\"numismatics\":{\"location\":\"Special Collections - Numismatics Collection\",\"library\":\"Special Collections\",\"location_code\":\"num\",\"call_number\":\"Coin 7321\",\"call_number_browse\":\"Coin 7321\"}}","numismatic_collection_s":["Antioch"],"numismatic_accession_s":["179: 1939-01-01 Antioch Excavation"],"pub_date_start_sort":335,"pub_date_end_sort":337,"issue_object_type_s":["coin"],"issue_denomination_s":["follis"],"issue_metal_s":["Bronze"],"issue_ruler_s":["Constantine I (306 to 337)"],"issue_workshop_s":["Antioch"],"issue_place_s":["Antioch, Syria, Roman Empire"],"issue_city_s":["Antioch"],"issue_state_s":["Syria"],"issue_region_s":["Roman Empire"],"issue_obverse_figure_s":["Bust"],"issue_obverse_orientation_s":["right"],"issue_obverse_figure_description_s":["laurelled, draped, cuirassed"],"issue_obverse_legend_s":["CONSTANTI-NVS MAX AVG"],"issue_reverse_figure_s":["Soldiers"],"issue_reverse_symbol_s":["T"],"issue_reverse_part_s":["standing"],"issue_reverse_orientation_s":["facing each other"],"issue_reverse_figure_description_s":["standard at center"],"issue_reverse_legend_s":["GLOR-IA EXERC-ITVS | SMAN"],"issue_references_s":["Cohen 7 377.114","RIC VII Antioch 108"],"issue_monogram_1display":"[]","issue_date_s":["335 to 337"],"hashed_id_s":["2c78711d15cb2af7"],"_version_":1691337603366780928,"timestamp":"2021-02-10T19:27:12.733Z"}