{
    "id": "coin-6970",
    "title_display": "Coin: 6970",
    "pub_created_display": [
        "quatrunx, Luceria"
    ],
    "call_number_display": [
        "Coin 6970"
    ],
    "call_number_browse_s": [
        "Coin 6970"
    ],
    "location_code_s": [
        "num"
    ],
    "location": [
        "Special Collections"
    ],
    "location_display": [
        "Special Collections - Numismatics Collection"
    ],
    "format": [
        "Coin"
    ],
    "advanced_location_s": [
        "num"
    ],
    "notes_display": [
        "Qautrunx is worth 4/10 as. Bought in Baldwin sale, 1926."
    ],
    "die_axis_s": [
        "12"
    ],
    "size_s": [
        "30"
    ],
    "technique_s": [
        "Cast"
    ],
    "weight_s": [
        "35.15"
    ],
    "holdings_1display": "{\"numismatics\":{\"location\":\"Special Collections - Numismatics Collection\",\"library\":\"Special Collections\",\"location_code\":\"num\",\"call_number\":\"Coin 6970\",\"call_number_browse\":\"Coin 6970\"}}",
    "pub_date_start_sort": -268,
    "pub_date_end_sort": -250,
    "issue_object_type_s": [
        "coin"
    ],
    "issue_denomination_s": [
        "quatrunx"
    ],
    "issue_number_s": [
        "4357"
    ],
    "issue_metal_s": [
        "Bronze"
    ],
    "issue_place_s": [
        "Luceria, Apulia, Italy"
    ],
    "issue_city_s": [
        "Luceria"
    ],
    "issue_state_s": [
        "Apulia"
    ],
    "issue_region_s": [
        "Italy"
    ],
    "issue_obverse_figure_s": [
        "Thunderbolt"
    ],
    "issue_reverse_figure_s": [
        "Club"
    ],
    "issue_reverse_symbol_s": [
        "4 dots"
    ],
    "issue_reverse_legend_s": [
        "L"
    ],
    "issue_references_s": [
        "Aes Grave: A Study of Cast Coinages of Rome and Central Italy pl. 15 139",
        "Haeb. pl. 71 18-20",
        "MIA pl. LXIV "
    ],
    "issue_monogram_1display": "[]",
    "hashed_id_s": [
        "86dc59fbaa382421"
    ],
    "_version_": 1667138359665885184,
    "timestamp": "2020-05-19T16:50:35.509Z"
}