{
    "id": "coin-2309",
    "title_display": "Coin: 2309",
    "pub_created_display": [
        "halfpence"
    ],
    "call_number_display": [
        "Coin 2309"
    ],
    "call_number_browse_s": [
        "Coin 2309"
    ],
    "location_code_s": [
        "num"
    ],
    "location": [
        "Special Collections"
    ],
    "location_display": [
        "Special Collections - Numismatics Collection"
    ],
    "format": [
        "Coin"
    ],
    "advanced_location_s": [
        "num"
    ],
    "notes_display": [
        "Edge reads \"PAYABLE IN LANCASTER LONDON OR BRISTOL"
    ],
    "die_axis_s": [
        "6"
    ],
    "size_s": [
        "29.5"
    ],
    "weight_s": [
        "12.19"
    ],
    "holdings_1display": "{\"numismatics\":{\"location\":\"Special Collections - Numismatics Collection\",\"library\":\"Special Collections\",\"location_code\":\"num\",\"call_number\":\"Coin 2309\",\"call_number_browse\":\"Coin 2309\"}}",
    "donor_s": [
        "W.S. Watson"
    ],
    "pub_date_start_sort": 0,
    "pub_date_end_sort": 0,
    "issue_object_type_s": [
        "coin"
    ],
    "issue_denomination_s": [
        "halfpence"
    ],
    "issue_number_s": [
        "1484"
    ],
    "issue_metal_s": [
        "Copper"
    ],
    "issue_master_s": [
        "John Hull"
    ],
    "issue_workshop_s": [
        "Westwood's, Birmingham, U.K."
    ],
    "issue_place_s": [
        "United States of America"
    ],
    "issue_region_s": [
        "United States of America"
    ],
    "issue_obverse_figure_s": [
        "Scroll"
    ],
    "issue_obverse_legend_s": [
        "UNANIMITY IS THE STRENGTH OF SOCIETY *"
    ],
    "issue_reverse_figure_s": [
        "15-star masonic pyramid"
    ],
    "issue_reverse_legend_s": [
        "E PLURIBUS UNUM"
    ],
    "issue_references_s": [
        "Breen  1156"
    ],
    "issue_monogram_1display": "[]",
    "hashed_id_s": [
        "8f42e6f4f733aaad"
    ],
    "_version_": 1667138219859247104,
    "timestamp": "2020-05-19T16:48:22.181Z"
}