{
    "id": "coin-6507",
    "title_display": "Coin: 6507",
    "pub_created_display": [
        "Didrachm, Tarentum"
    ],
    "call_number_display": [
        "Coin 6507"
    ],
    "call_number_browse_s": [
        "Coin 6507"
    ],
    "location_code_s": [
        "num"
    ],
    "location": [
        "Special Collections"
    ],
    "location_display": [
        "Special Collections - Numismatics Collection"
    ],
    "format": [
        "Coin"
    ],
    "advanced_location_s": [
        "num"
    ],
    "notes_display": [
        "F-B O: 396, R: 604"
    ],
    "die_axis_s": [
        "6"
    ],
    "size_s": [
        "22"
    ],
    "weight_s": [
        "7.6"
    ],
    "holdings_1display": "{\"numismatics\":{\"location\":\"Special Collections - Numismatics Collection\",\"library\":\"Special Collections\",\"location_code\":\"num\",\"call_number\":\"Coin 6507\",\"call_number_browse\":\"Coin 6507\"}}",
    "donor_s": [
        "Baldwin Maull"
    ],
    "pub_date_start_sort": -340,
    "pub_date_end_sort": -325,
    "issue_object_type_s": [
        "coin"
    ],
    "issue_denomination_s": [
        "Didrachm"
    ],
    "issue_number_s": [
        "3928"
    ],
    "issue_metal_s": [
        "Silver"
    ],
    "issue_place_s": [
        "Tarentum, Calabria, Italy"
    ],
    "issue_city_s": [
        "Tarentum"
    ],
    "issue_state_s": [
        "Calabria"
    ],
    "issue_region_s": [
        "Italy"
    ],
    "issue_obverse_figure_s": [
        "Rider on standing horse"
    ],
    "issue_obverse_symbol_s": [
        "SIM"
    ],
    "issue_obverse_orientation_s": [
        "right"
    ],
    "issue_obverse_figure_description_s": [
        "rider crowns  horse, reins in left hand; horse lifts its left front hoof; to the left, Nike flying holds forth a band with which to wreath the rider; SIM below the horse's belly"
    ],
    "issue_reverse_figure_s": [
        "Boy on a dolphin"
    ],
    "issue_reverse_symbol_s": [
        "[heta][eta][rho], AR"
    ],
    "issue_reverse_orientation_s": [
        "left"
    ],
    "issue_reverse_figure_description_s": [
        "boy holds kantharos in outstretched right hand, left hand holds trident crooked in arm; heta-eta-rho below dolphin; waves below"
    ],
    "issue_references_s": [
        "Vlasto Coll.  503-4",
        "F-B  778"
    ],
    "issue_monogram_1display": "[]",
    "hashed_id_s": [
        "0c01241602548782"
    ],
    "_version_": 1667138373036277760,
    "timestamp": "2020-05-19T16:50:48.262Z"
}