{"id":"coin-8505","title_display":"Coin: 8505","pub_created_display":["Unknown, Antioch"],"call_number_display":["Coin 8505"],"call_number_browse_s":["Coin 8505"],"location_code_s":["num"],"location":["Special Collections"],"location_display":["Special Collections - Numismatics Collection"],"format":["Coin"],"advanced_location_s":["num"],"notes_display":["Both sides of coin worn away and illegible"],"find_place_s":["Antioch, Syria"],"find_date_s":["5/13/1937"],"find_locus_s":["17-O"],"find_number_s":["Ca917"],"die_axis_s":["6"],"size_s":["12"],"weight_s":["1.14"],"holdings_1display":"{\"numismatics\":{\"location\":\"Special Collections - Numismatics Collection\",\"library\":\"Special Collections\",\"location_code\":\"num\",\"call_number\":\"Coin 8505\",\"call_number_browse\":\"Coin 8505\"}}","numismatic_collection_s":["Antioch"],"numismatic_accession_s":["179: 1939-01-01 Antioch Excavation"],"pub_date_start_sort":300,"pub_date_end_sort":500,"issue_object_type_s":["coin"],"issue_metal_s":["Bronze"],"issue_ruler_s":["Unknown"],"issue_place_s":["Antioch, Syria, Roman Empire"],"issue_city_s":["Antioch"],"issue_state_s":["Syria"],"issue_region_s":["Roman Empire"],"issue_obverse_figure_s":["Emperor"],"issue_obverse_part_s":["bust"],"issue_obverse_orientation_s":["right"],"issue_obverse_legend_s":["Illegible"],"issue_reverse_legend_s":["Illegible"],"issue_references_s":["Waage  "],"issue_monogram_1display":"[]","issue_date_s":["300 to 500"],"hashed_id_s":["c411a611d2cd2b53"],"_version_":1684903422002724864,"timestamp":"2020-12-01T18:58:39.192Z"}