{
    "id": "coin-6064",
    "title_display": "Coin: 6064",
    "pub_created_display": [
        "Anastasius I (491 to 518), 5 nummi, Antioch"
    ],
    "call_number_display": [
        "Coin 6064"
    ],
    "call_number_browse_s": [
        "Coin 6064"
    ],
    "location_code_s": [
        "num"
    ],
    "location": [
        "Special Collections"
    ],
    "location_display": [
        "Special Collections - Numismatics Collection"
    ],
    "format": [
        "Coin"
    ],
    "advanced_location_s": [
        "num"
    ],
    "notes_display": [
        "Attribution uncertain, possibly Anastasius or Justinian"
    ],
    "find_place_s": [
        "Antioch, Syria"
    ],
    "find_date_s": [
        "5/24/1932"
    ],
    "find_feature_s": [
        "house A surface"
    ],
    "find_locus_s": [
        "N-10"
    ],
    "find_number_s": [
        "1760"
    ],
    "die_axis_s": [
        "3"
    ],
    "size_s": [
        "12"
    ],
    "weight_s": [
        "1.83"
    ],
    "holdings_1display": "{\"numismatics\":{\"location\":\"Special Collections - Numismatics Collection\",\"library\":\"Special Collections\",\"location_code\":\"num\",\"call_number\":\"Coin 6064\",\"call_number_browse\":\"Coin 6064\"}}",
    "pub_date_start_sort": 491,
    "pub_date_end_sort": 518,
    "issue_object_type_s": [
        "coin"
    ],
    "issue_denomination_s": [
        "5 nummi"
    ],
    "issue_number_s": [
        "3529"
    ],
    "issue_metal_s": [
        "Bronze"
    ],
    "issue_ruler_s": [
        "Anastasius I (491 to 518)"
    ],
    "issue_workshop_s": [
        "uncertain"
    ],
    "issue_place_s": [
        "Antioch, Syria, Byzantium"
    ],
    "issue_city_s": [
        "Antioch"
    ],
    "issue_state_s": [
        "Syria"
    ],
    "issue_region_s": [
        "Byzantium"
    ],
    "issue_obverse_figure_s": [
        "Emperor"
    ],
    "issue_obverse_part_s": [
        "bust"
    ],
    "issue_obverse_orientation_s": [
        "right"
    ],
    "issue_obverse_legend_s": [
        "uncertain"
    ],
    "issue_reverse_symbol_s": [
        "\u0404"
    ],
    "issue_reverse_legend_s": [
        "uncertain"
    ],
    "issue_references_s": [
        "BMC.Byz.  72",
        "MIB  63",
        "DOC  49d",
        "BN  page 33, 05"
    ],
    "issue_monogram_1display": "[]",
    "hashed_id_s": [
        "fa459929f561007a"
    ],
    "_version_": 1667138382465073152,
    "timestamp": "2020-05-19T16:50:57.254Z"
}