{
    "id": "coin-10396",
    "title_display": "Coin: 10396",
    "pub_created_display": [
        "Galba (68 to 69), denarius, Rome"
    ],
    "call_number_display": [
        "Coin 10396"
    ],
    "call_number_browse_s": [
        "Coin 10396"
    ],
    "location_code_s": [
        "num"
    ],
    "location": [
        "Special Collections"
    ],
    "location_display": [
        "Special Collections - Numismatics Collection"
    ],
    "format": [
        "Coin"
    ],
    "advanced_location_s": [
        "num"
    ],
    "die_axis_s": [
        "6"
    ],
    "size_s": [
        "19"
    ],
    "weight_s": [
        "3.01"
    ],
    "holdings_1display": "{\"numismatics\":{\"location\":\"Special Collections - Numismatics Collection\",\"library\":\"Special Collections\",\"location_code\":\"num\",\"call_number\":\"Coin 10396\",\"call_number_browse\":\"Coin 10396\"}}",
    "pub_date_start_sort": 68,
    "pub_date_end_sort": 69,
    "issue_object_type_s": [
        "coin"
    ],
    "issue_denomination_s": [
        "denarius"
    ],
    "issue_metal_s": [
        "Silver"
    ],
    "issue_ruler_s": [
        "Galba (68 to 69)"
    ],
    "issue_place_s": [
        "Rome, Italy, Roman Empire"
    ],
    "issue_city_s": [
        "Rome"
    ],
    "issue_state_s": [
        "Italy"
    ],
    "issue_region_s": [
        "Roman Empire"
    ],
    "issue_obverse_figure_s": [
        "Galba"
    ],
    "issue_obverse_orientation_s": [
        "right"
    ],
    "issue_obverse_figure_description_s": [
        "Bare head of Galba, right"
    ],
    "issue_obverse_legend_s": [
        "IMP SER GALBA AVG"
    ],
    "issue_reverse_symbol_s": [
        "oak wreath"
    ],
    "issue_reverse_orientation_s": [
        "encircling"
    ],
    "issue_reverse_legend_s": [
        "S P Q R / OB / C S"
    ],
    "issue_references_s": [
        "Roman Imperial Coinage  167"
    ],
    "issue_monogram_1display": "[]",
    "issue_date_s": [
        "68 to 69"
    ],
    "hashed_id_s": [
        "9ea28c8d4d348b37"
    ],
    "_version_": 1684903432723365888,
    "timestamp": "2020-12-01T18:58:49.416Z"
}