{"id":"coin-6199","title_display":"Coin: 6199","call_number_display":["Coin 6199"],"call_number_browse_s":["Coin 6199"],"location_code_s":["num"],"location":["Special Collections"],"location_display":["Special Collections - Numismatics Collection"],"format":["Coin"],"advanced_location_s":["num"],"counter_stamp_s":["L150, April 26, 9, One Hundred Fifty Pounds, Stephen Minots, J Mascorens, H. Gardner"],"size_s":["147x225"],"holdings_1display":"{\"numismatics\":{\"location\":\"Special Collections - Numismatics Collection\",\"library\":\"Special Collections\",\"location_code\":\"num\",\"call_number\":\"Coin 6199\",\"call_number_browse\":\"Coin 6199\"}}","numismatic_collection_s":["Firestone"],"numismatic_accession_s":["1:  "],"pub_date_start_sort":0,"pub_date_end_sort":0,"issue_object_type_s":["check"],"issue_metal_s":["Paper"],"issue_workshop_s":["Massachusetts Treasury"],"issue_series_s":["April 26, 1780"],"issue_place_s":["Massachusetts, United States of America"],"issue_state_s":["Massachusetts"],"issue_region_s":["United States of America"],"issue_obverse_figure_description_s":["Check issued as advance pay to officers."],"issue_obverse_legend_s":["State of Massachusetts Bay | April 26, 1779 | FOR Value received for the Use of the State of Massachusetts-Bay, I do in behalf of said State hereby promise and oblige Myself and Successors in the Office of Treasurer to pay the Possessor of this Note the Sum of One Hundred Fifty Pounds by the First Day of January 1780, with Interest at Six per Cent per Annum. -Interest to commence on the Fifteenth Day of April 1779. Witness my Hand. H. Gardner, Treasurer | DEATH TO COUNTERFEIT THIS."],"issue_monogram_1display":"[]","hashed_id_s":["d648a84bc6445a35"],"_version_":1684902962230460416,"timestamp":"2020-12-01T18:51:20.719Z"}